Metadata-Version: 1.1
Name: pyshop
Version: 1.2.5
Summary: Private Python Package Index
Home-page: https://github.com/mardiros/pyshop
Author: Guillaume Gauvrit
Author-email: guillaume@gauvr.it
License: UNKNOWN
Keywords: web wsgi pyramid cheeseshop pypi packaging
Platform: UNKNOWN
Classifier: Programming Language :: Python
Classifier: Programming Language :: Python :: 2.6
Classifier: Programming Language :: Python :: 2.7
Classifier: Programming Language :: Python :: 3.3
Classifier: Programming Language :: Python :: 3.4
Classifier: Development Status :: 5 - Production/Stable
Classifier: Environment :: Web Environment
Classifier: Framework :: Pyramid
Classifier: Topic :: Internet :: WWW/HTTP
Classifier: Topic :: Internet :: WWW/HTTP :: WSGI :: Application
Classifier: Topic :: Software Development
Classifier: Topic :: System :: Archiving :: Mirroring
Classifier: Topic :: System :: Archiving :: Packaging
Classifier: Intended Audience :: Developers
Classifier: Intended Audience :: System Administrators
Classifier: License :: OSI Approved :: BSD License
